{
  "permits": [
    {
      "id": "BLDR2603159",
      "isNew": true,
      "bucket": "fa",
      "address": "3875 N 371ST AVE TONOPAH AZ 85354",
      "zip": "85354",
      "status": "Requires Customer Attention",
      "statusLabel": "Requires Customer Attention",
      "applied": "2026-04-22",
      "issued": null,
      "expire": null,
      "finaled": null,
      "parcel": "—",
      "description": "6.630 kW DC Roof Mounted Solar",
      "systemKW": 6.63,
      "battery": false,
      "batteryModel": null,
      "contractor": null,
      "licenseROC": null,
      "contractorPhone": null,
      "contractorEmail": null,
      "valuation": null,
      "owner": null,
      "ownerType": null,
      "lastSold": null,
      "parcelType": null,
      "satelliteStatus": "clear",
      "lat": 33.490792,
      "lng": -112.850337,
      "coordSource": "census",
      "portalUrl": "https://maricopacountyaz-energovweb.tylerhost.net/apps/selfservice#/permit/BLDR2603159",
      "notes": "Assumption: ZIP centroid offset. Applied 1 day ago — hottest fresh lead."
    },
    {
      "id": "BLDR2603076",
      "isNew": true,
      "bucket": "fa",
      "address": "43418 W ENCANTO BLVD TONOPAH AZ 85354",
      "zip": "85354",
      "status": "In Review",
      "statusLabel": "In Review",
      "applied": "2026-04-20",
      "issued": null,
      "expire": null,
      "finaled": null,
      "parcel": "—",
      "description": "INSTALLATION OF A 11.50 KW (AC) PV SYSTEM + BATTERY INTEGRATED // INSTALL PER MANUFACTURER'S RECOMMENDATION AND 2017 NEC ARTICLES 690 & 705",
      "systemKW": 11.5,
      "battery": true,
      "batteryModel": "Battery Integrated",
      "contractor": null,
      "licenseROC": null,
      "contractorPhone": null,
      "contractorEmail": null,
      "valuation": null,
      "owner": null,
      "ownerType": null,
      "lastSold": null,
      "parcelType": null,
      "satelliteStatus": "verify",
      "lat": 33.4348,
      "lng": -112.9083,
      "coordSource": "nominatim",
      "portalUrl": "https://maricopacountyaz-energovweb.tylerhost.net/apps/selfservice#/permit/BLDR2603076",
      "notes": "Applied 3 days ago. 11.5 kW system with integrated battery — large system. Satellite check needed."
    },
    {
      "id": "BLDR2603069",
      "isNew": true,
      "bucket": "fa",
      "address": "302 4TH AVE BUCKEYE AZ 85326",
      "zip": "85326",
      "status": "In Review",
      "statusLabel": "In Review",
      "applied": "2026-04-20",
      "issued": null,
      "expire": null,
      "finaled": null,
      "parcel": "—",
      "description": "INSTALLATION OF A 11 MODULES - ROOF MOUNTED - 4.510 kW DC, 1 BATTERY MODULE // INSTALL PER MANUFACTURER'S RECOMMENDATION AND 2017 NEC ARTICLES 690 & 705",
      "systemKW": 4.51,
      "battery": true,
      "batteryModel": null,
      "contractor": null,
      "licenseROC": null,
      "contractorPhone": null,
      "contractorEmail": null,
      "valuation": null,
      "owner": null,
      "ownerType": null,
      "lastSold": null,
      "parcelType": null,
      "satelliteStatus": "clear",
      "lat": 33.380823,
      "lng": -112.57987,
      "coordSource": "census",
      "portalUrl": "https://maricopacountyaz-energovweb.tylerhost.net/apps/selfservice#/permit/BLDR2603069",
      "notes": "Applied 3 days ago. 11 modules, 4.51 kW DC. Battery included. Buckeye in-town address."
    },
    {
      "id": "BLDR2602943",
      "isNew": true,
      "bucket": "fa",
      "address": "12856 S ZUNI RD BUCKEYE AZ 85326",
      "zip": "85326",
      "status": "Requires Customer Attention",
      "statusLabel": "Requires Customer Attention",
      "applied": "2026-04-15",
      "issued": null,
      "expire": null,
      "finaled": null,
      "parcel": "—",
      "description": "NEW PHOTOVOLTAIC PITCHED ROOF MOUNTED SYSTEM - 12.150 KW DC/9.600 KW AC WITH BATTERY STORAGE SYSTEM // INSTALL PER MANUFACTURER'S RECOMMENDATION AND 2017 NEC ARTICLES 690 & 705",
      "systemKW": 12.15,
      "battery": true,
      "batteryModel": null,
      "contractor": null,
      "licenseROC": null,
      "contractorPhone": null,
      "contractorEmail": null,
      "valuation": null,
      "owner": null,
      "ownerType": null,
      "lastSold": null,
      "parcelType": null,
      "satelliteStatus": "solar-detected",
      "lat": 33.329575,
      "lng": -112.486243,
      "coordSource": "census",
      "portalUrl": "https://maricopacountyaz-energovweb.tylerhost.net/apps/selfservice#/permit/BLDR2602943",
      "notes": "Requires Customer Attention — customer may need to respond to proceed. Applied 8 days ago. 12.15 kW DC / 9.6 kW AC — large residential system with battery."
    },
    {
      "id": "BLDR2602638",
      "isNew": false,
      "bucket": "fa",
      "address": "36923 W MONROE ST TONOPAH AZ 85354",
      "zip": "85354",
      "status": "Requires Customer Attention",
      "statusLabel": "Requires Customer Attention",
      "applied": "2026-04-03",
      "issued": null,
      "expire": null,
      "finaled": null,
      "parcel": "506-41-113H",
      "description": "7.020 kW DC ROOF MOUNTED SOLAR",
      "systemKW": 7.02,
      "battery": false,
      "batteryModel": null,
      "contractor": null,
      "licenseROC": null,
      "contractorPhone": null,
      "contractorEmail": null,
      "valuation": null,
      "owner": "RD DESIGN TEAM INC",
      "ownerType": "Entity",
      "lastSold": null,
      "parcelType": "Land",
      "satelliteStatus": "verify",
      "lat": 33.447924,
      "lng": -112.846898,
      "coordSource": "nominatim",
      "portalUrl": "https://maricopacountyaz-energovweb.tylerhost.net/apps/selfservice#/permit/621d6fb4-9ef4-4cef-baef-0de36d879ce6",
      "notes": ""
    },
    {
      "id": "BLDR2601598",
      "isNew": false,
      "bucket": "fa",
      "address": "37203 W HILTON AVE TONOPAH AZ 85354",
      "zip": "85354",
      "status": "Fees Due",
      "statusLabel": "Fees Due",
      "applied": "2026-02-27",
      "issued": null,
      "expire": null,
      "finaled": null,
      "parcel": "506-41-139D",
      "description": "ROOF MOUNTED APS GRID TIE PHOTOVOLTAIC SYSTEM ON EXISTING MANUFACTURED HOME // INTEGRATED TESLA BATTERY // INSTALL PER MANUFACTURER'S RECOMMENDATION AND 2017 NEC ARTICLES 690 & 705",
      "systemKW": null,
      "battery": true,
      "batteryModel": "Tesla Integrated (Powerwall 3)",
      "contractor": null,
      "licenseROC": null,
      "contractorPhone": null,
      "contractorEmail": null,
      "valuation": null,
      "owner": "WEAVER LOGAN",
      "ownerType": "Individual",
      "lastSold": "2025-11-01",
      "parcelType": "Mobile Home",
      "satelliteStatus": "clear",
      "lat": 33.426013,
      "lng": -112.853354,
      "coordSource": "nominatim",
      "portalUrl": "https://maricopacountyaz-energovweb.tylerhost.net/apps/selfservice#/permit/0996b598-8a02-4fb4-a633-60515770fd41",
      "notes": ""
    },
    {
      "id": "BLDR2600845",
      "isNew": false,
      "bucket": "fa",
      "address": "22211 W WILDFLOWER DR WITTMANN AZ 85361",
      "zip": "85361",
      "status": "In Review",
      "statusLabel": "In Review",
      "applied": "2026-02-03",
      "issued": null,
      "expire": null,
      "finaled": null,
      "parcel": "503-39-081",
      "description": "ROOF MOUNTED APS GRID TIE PHOTOVOLTAIC SYSTEM // INTEGRATED TESLA BATTERY // ON EXISTING MANUFACTURED HOME // INSTALL PER MANUFACTURER'S RECOMMENDATION AND 2017 NEC ARTICLES 690 & 705",
      "systemKW": null,
      "battery": true,
      "batteryModel": "Tesla Integrated (Powerwall 3)",
      "contractor": null,
      "licenseROC": null,
      "contractorPhone": null,
      "contractorEmail": null,
      "valuation": null,
      "owner": "MAKULA LAURA ANN/CHARLES JOHN III",
      "ownerType": "Individual",
      "lastSold": "2021-12-01",
      "parcelType": "Mobile Home",
      "satelliteStatus": "clear",
      "lat": 33.777415,
      "lng": -112.54035,
      "coordSource": "nominatim",
      "portalUrl": "https://maricopacountyaz-energovweb.tylerhost.net/apps/selfservice#/permit/6841a8dc-91fe-4f5d-b2a1-21662e35544d",
      "notes": "In Review for 79 days — unusually long review. Manufactured home. Tesla Integrated battery."
    },
    {
      "id": "BLDR2506807",
      "isNew": false,
      "bucket": "fa",
      "address": "22347 W PATTON RD WITTMANN AZ 85361",
      "zip": "85361",
      "status": "In Review",
      "statusLabel": "In Review",
      "applied": "2025-08-25",
      "issued": null,
      "expire": null,
      "finaled": null,
      "parcel": "503-34-018F",
      "description": "ROOF MOUNTED APS GRID TIE PHOTOVOLTAIC SYSTEM INSTALL PER MANUFACTURER'S RECOMMENDATION AND 2017 NEC ARTICLES 690 & 705",
      "systemKW": null,
      "battery": false,
      "batteryModel": null,
      "contractor": null,
      "licenseROC": null,
      "contractorPhone": null,
      "contractorEmail": null,
      "valuation": null,
      "owner": "MCHENRY MATTHEW",
      "ownerType": "Individual",
      "lastSold": null,
      "parcelType": "Residential",
      "satelliteStatus": "clear",
      "lat": 33.738616,
      "lng": -112.544695,
      "coordSource": "census",
      "portalUrl": "https://maricopacountyaz-energovweb.tylerhost.net/apps/selfservice#/permit/f628309b-f565-480d-972d-f1142b7dcab3",
      "notes": "In Review for 241 DAYS — extremely stalled pre-issuance. Owner MCHENRY MATTHEW. No battery — retrofit opp. Worth a door knock."
    },
    {
      "id": "BLDR2505482",
      "isNew": true,
      "bucket": "fa",
      "address": "20435 W ELLIOT RD BUCKEYE AZ 85326",
      "zip": "85326",
      "status": "In Review",
      "statusLabel": "In Review",
      "applied": "2025-07-10",
      "issued": null,
      "expire": null,
      "finaled": null,
      "parcel": "—",
      "description": "ROOF MOUNTED APS GRID TIE PHOTOVOLTAIC SYSTEM//SOLAREDGE BATTERY// WHICH INCLUDES REDUCTION OF MAIN CIRCUIT BREAKER TO 175 AMPS // INSTALL PER MANUFACTURER'S RECOMMENDATION AND 2017 NEC ARTICLES 690 & 705",
      "systemKW": null,
      "battery": true,
      "batteryModel": "SolarEdge Home Battery",
      "contractor": null,
      "licenseROC": null,
      "contractorPhone": null,
      "contractorEmail": null,
      "valuation": null,
      "owner": null,
      "ownerType": null,
      "lastSold": null,
      "parcelType": null,
      "satelliteStatus": "solar-detected",
      "lat": 33.348369,
      "lng": -112.490971,
      "coordSource": "census",
      "portalUrl": "https://maricopacountyaz-energovweb.tylerhost.net/apps/selfservice#/permit/BLDR2505482",
      "notes": "In Review for 288 DAYS — very stalled. SolarEdge battery + main breaker reduction to 175A. Prime door-knock lead."
    },
    {
      "id": "BLDR2600204",
      "isNew": false,
      "bucket": "fa",
      "address": "32828 N 228TH DR WITTMANN AZ 85361",
      "zip": "85361",
      "status": "Fees Due",
      "statusLabel": "Fees Due",
      "applied": "2026-01-12",
      "issued": "2026-01-26",
      "expire": "2026-07-25",
      "finaled": null,
      "parcel": "503-17-007N",
      "description": "ROOF MOUNTED APS GRID TIE PHOTOVOLTAIC SYSTEM // INTEGRATED TESLA BATTERY // INSTALL PER MANUFACTURER'S RECOMMENDATION AND 2017 NEC ARTICLES 690 & 705",
      "systemKW": null,
      "battery": true,
      "batteryModel": "Tesla Integrated (Powerwall 3)",
      "contractor": null,
      "licenseROC": null,
      "contractorPhone": null,
      "contractorEmail": null,
      "valuation": null,
      "owner": "BERES KEITH R/CALVIN-BERES DEBRA",
      "ownerType": "Individual",
      "lastSold": "2025-09-01",
      "parcelType": "Residential",
      "satelliteStatus": "clear",
      "lat": 33.781029,
      "lng": -112.554381,
      "coordSource": "census",
      "portalUrl": "https://maricopacountyaz-energovweb.tylerhost.net/apps/selfservice#/permit/c553d056-dd29-4adb-a1a3-cd672239dbc5",
      "notes": "Fees Due AFTER issuance — unusual. Permit was issued Jan 26 but now fees owed. Recent buyer (Sep 2025). Tesla Integrated battery. Assumption: issueDays calc bypassed since status is Fees Due (pre-issuance bucket)."
    },
    {
      "id": "BLDR2602145",
      "isNew": false,
      "bucket": "pi",
      "address": "1127 N 381ST DR TONOPAH AZ 85354",
      "zip": "85354",
      "status": "Issued",
      "statusLabel": "Issued",
      "applied": "2026-03-18",
      "issued": "2026-03-19",
      "expire": "2026-10-14",
      "finaled": null,
      "parcel": "506-45-295B",
      "description": "ROOF MOUNTED APS GRID TIE PHOTOVOLTAIC SYSTEM // INTEGRATED TESLA BATTERY // INSTALL PER MANUFACTURER'S RECOMMENDATION AND 2017 NEC ARTICLES 690 & 705",
      "systemKW": null,
      "battery": true,
      "batteryModel": "Tesla Integrated (Powerwall 3)",
      "contractor": "Empower Electric Solar",
      "licenseROC": "346621",
      "contractorPhone": "800-306-6953",
      "contractorEmail": "arizonapermits@empoweryourhome.com",
      "valuation": 27681,
      "owner": "Joy L, James M & Deborah Dement",
      "ownerType": "Individual",
      "lastSold": "2018-07-01",
      "parcelType": "Mobile Home",
      "satelliteStatus": "clear",
      "lat": 33.459397,
      "lng": -112.872855,
      "coordSource": "census",
      "portalUrl": "https://maricopacountyaz-energovweb.tylerhost.net/apps/selfservice#/permit/f4e4f21b-4d66-4d7d-bce8-4de6e0f8a96e",
      "notes": "",
      "outcome": "hassolar",
      "outcomeDate": "2026-04-24T01:23:19.497Z"
    },
    {
      "id": "BLDR2600318",
      "isNew": false,
      "bucket": "pi",
      "address": "22503 W PATTON RD WITTMANN AZ 85361",
      "zip": "85361",
      "status": "Issued",
      "statusLabel": "Issued",
      "applied": "2026-01-15",
      "issued": "2026-03-16",
      "expire": "2026-09-12",
      "finaled": null,
      "parcel": "503-34-016T",
      "description": "ROOF MOUNTED APS GRID TIE PHOTOVOLTAIC SYSTEM // INTEGRATED TESLA BATTERY // INSTALL PER MANUFACTURER'S RECOMMENDATION AND 2017 NEC ARTICLES 690 & 705",
      "systemKW": null,
      "battery": true,
      "batteryModel": "Tesla Integrated (Powerwall 3)",
      "contractor": "Freedom Forever Arizona",
      "licenseROC": "",
      "contractorPhone": "602-888-7196",
      "contractorEmail": "permitsarizona@freedomforever.com",
      "valuation": 53888,
      "owner": "Eric J Ramsdell & Amber B Gaszsi-Ramsdell",
      "ownerType": "Individual",
      "lastSold": null,
      "parcelType": "Residential",
      "satelliteStatus": "clear",
      "lat": 33.738616,
      "lng": -112.547971,
      "coordSource": "census",
      "portalUrl": "https://maricopacountyaz-energovweb.tylerhost.net/apps/selfservice#/permit/dae8f6e0-a6f5-43ab-acdf-a08bf4aa194d",
      "notes": "Issued 38 days ago. Freedom Forever AZ. Est kW: ≈22.0 kW (est from $53,888 - $10,000 / $2,000) — large system. Satellite was clear previously — reverify."
    },
    {
      "id": "BLDR2601941",
      "isNew": false,
      "bucket": "pi",
      "address": "6215 S EL MIRAGE RD TOLLESON AZ 85353",
      "zip": "85353",
      "status": "Issued",
      "statusLabel": "Issued",
      "applied": "2026-03-11",
      "issued": "2026-03-12",
      "expire": "2026-09-08",
      "finaled": null,
      "parcel": "500-69-032",
      "description": "ROOF MOUNTED APS GRID TIE PHOTOVOLTAIC SYSTEM // TESLA POWERWALL 3 BATTERY // WITH MAIN SERVICE PANEL UPGRADE TO 225A SOLAR READY // INSTALL PER MANUFACTURER'S RECOMMENDATION AND 2017 NEC ARTICLES 690 & 705",
      "systemKW": null,
      "battery": true,
      "batteryModel": "Tesla Powerwall 3",
      "contractor": null,
      "licenseROC": null,
      "contractorPhone": null,
      "contractorEmail": null,
      "valuation": null,
      "owner": "EDWARD A AND GAYLE L BALKE TRUST",
      "ownerType": "Entity",
      "lastSold": null,
      "parcelType": "Residential",
      "satelliteStatus": "clear",
      "lat": 33.388703,
      "lng": -112.323083,
      "coordSource": "census",
      "portalUrl": "https://maricopacountyaz-energovweb.tylerhost.net/apps/selfservice#/permit/edcd1f1d-9e69-46a7-b96b-e216744071bb",
      "notes": "Issued 42 days ago. Tesla Powerwall 3 + MPU to 225A Solar Ready. Trust ownership. Tolleson — edge of territory. Satellite check needed."
    },
    {
      "id": "BLDR2601231",
      "isNew": false,
      "bucket": "ry",
      "address": "805 S 348TH AVE TONOPAH AZ 85354",
      "zip": "85354",
      "status": "Issued",
      "statusLabel": "Issued — STALLED 62 days",
      "applied": "2026-02-16",
      "issued": "2026-02-20",
      "expire": "2026-09-12",
      "finaled": null,
      "parcel": "504-12-005T",
      "description": "ROOF MOUNTED APS GRID TIE PHOTOVOLTAIC SYSTEM // (2) TESLA POWERWALL 3 BATTERY // INSTALL PER MANUFACTURER'S RECOMMENDATION AND 2017 NEC ARTICLES 690 & 705",
      "systemKW": null,
      "battery": true,
      "batteryModel": "Tesla Powerwall 3 (x2)",
      "contractor": "Our World Energy",
      "licenseROC": "",
      "contractorPhone": "623-850-5700",
      "contractorEmail": "permits@ourworldenergy.com",
      "valuation": 27150,
      "owner": "James Edwin Moreland Jr & Shana A",
      "ownerType": "Individual",
      "lastSold": "2019-03-01",
      "parcelType": "Mobile Home",
      "satelliteStatus": "clear",
      "lat": 33.43922,
      "lng": -112.800849,
      "coordSource": "census",
      "portalUrl": "https://maricopacountyaz-energovweb.tylerhost.net/apps/selfservice#/permit/ac7269ff-6e1d-4b74-b168-0a659efa0120",
      "notes": "",
      "outcome": "hassolar",
      "outcomeDate": "2026-04-24T01:27:54.730Z"
    },
    {
      "id": "BLDR2600729",
      "isNew": false,
      "bucket": "ry",
      "address": "38402 W LATHAM ST TONOPAH AZ 85354",
      "zip": "85354",
      "status": "Issued",
      "statusLabel": "Issued — STALLED 63 days",
      "applied": "2026-01-30",
      "issued": "2026-02-19",
      "expire": "2026-08-18",
      "finaled": null,
      "parcel": "506-45-350",
      "description": "ROOF MOUNTED APS GRID TIE PHOTOVOLTAIC SYSTEM ON EXISTING MANUFACTURED HOME // INSTALL PER MANUFACTURER'S RECOMMENDATION AND 2017 NEC ARTICLES 690 & 705",
      "systemKW": null,
      "battery": false,
      "batteryModel": null,
      "contractor": "Capital Energy LLC",
      "licenseROC": "",
      "contractorPhone": "480-896-5847",
      "contractorEmail": "permits@cptlenergy.com",
      "valuation": 9917,
      "owner": "Anthony Angulo Borboa",
      "ownerType": "Individual",
      "lastSold": "2026-01-01",
      "parcelType": "Mobile Home",
      "satelliteStatus": "clear",
      "lat": 33.459298,
      "lng": -112.878376,
      "coordSource": "census",
      "portalUrl": "https://maricopacountyaz-energovweb.tylerhost.net/apps/selfservice#/permit/8cf572c0-817f-42be-b67b-c5e5c38de634",
      "notes": "",
      "outcome": "hassolar",
      "outcomeDate": "2026-04-24T01:39:42.604Z"
    },
    {
      "id": "BLDR2600280",
      "isNew": false,
      "bucket": "ry",
      "address": "36915 W MONROE ST TONOPAH AZ 85354",
      "zip": "85354",
      "status": "Withdrawn",
      "statusLabel": "Withdrawn",
      "applied": "2026-01-14",
      "issued": null,
      "expire": null,
      "finaled": null,
      "parcel": "506-41-113J",
      "description": "Install 5.67kW PV Solar (roof mounted)",
      "systemKW": 5.67,
      "battery": false,
      "batteryModel": null,
      "contractor": null,
      "licenseROC": null,
      "contractorPhone": null,
      "contractorEmail": null,
      "valuation": null,
      "owner": "GUIZA AARON AGUILERA/CANO MARIA D FARIAS",
      "ownerType": "Individual",
      "lastSold": "2025-11-01",
      "parcelType": "Land",
      "satelliteStatus": "verify",
      "lat": 33.447924,
      "lng": -112.846356,
      "coordSource": "nominatim",
      "portalUrl": "https://maricopacountyaz-energovweb.tylerhost.net/apps/selfservice#/permit/c72916f8-9ee3-433a-911e-a4a7dffb75f0",
      "notes": "",
      "outcome": "hassolar",
      "outcomeDate": "2026-04-24T01:21:47.655Z"
    },
    {
      "id": "BLDR2509990",
      "isNew": false,
      "bucket": "ry",
      "address": "34811 W BUCKEYE RD TONOPAH AZ 85354",
      "zip": "85354",
      "status": "Issued",
      "statusLabel": "Issued — STALLED 122 days",
      "applied": "2025-12-16",
      "issued": "2025-12-22",
      "expire": "2026-07-13",
      "finaled": null,
      "parcel": "504-12-082F",
      "description": "ROOF MOUNTED APS GRID TIE PHOTOVOLTAIC SYSTEM INSTALL PER MANUFACTURER'S RECOMMENDATION AND 2017 NEC ARTICLES 690 & 705",
      "systemKW": null,
      "battery": false,
      "batteryModel": null,
      "contractor": null,
      "licenseROC": null,
      "contractorPhone": null,
      "contractorEmail": null,
      "valuation": null,
      "owner": "KALAR LONNIE/ROBERTA",
      "ownerType": "Individual",
      "lastSold": "2025-11-01",
      "parcelType": "Residential",
      "satelliteStatus": "clear",
      "lat": 33.435541,
      "lng": -112.801207,
      "coordSource": "census",
      "portalUrl": "https://maricopacountyaz-energovweb.tylerhost.net/apps/selfservice#/permit/e548f0aa-238b-415d-b5dc-d43e78b48510",
      "notes": ""
    },
    {
      "id": "BLDR2509583",
      "isNew": false,
      "bucket": "ry",
      "address": "3212 N 367TH AVE TONOPAH AZ 85354",
      "zip": "85354",
      "status": "Withdrawn",
      "statusLabel": "Withdrawn",
      "applied": "2025-12-02",
      "issued": null,
      "expire": null,
      "finaled": null,
      "parcel": "506-40-175J",
      "description": "Installation of a 8.800 kW rooftop mounted photovoltaic system with battery storage system.",
      "systemKW": 8.8,
      "battery": true,
      "batteryModel": null,
      "contractor": null,
      "licenseROC": null,
      "contractorPhone": null,
      "contractorEmail": null,
      "valuation": null,
      "owner": "QUINTANA MANUEL G/QUINTANA AVILA MARIA E",
      "ownerType": "Individual",
      "lastSold": "2017-12-01",
      "parcelType": "Mobile Home",
      "satelliteStatus": "clear",
      "lat": 33.416939,
      "lng": -112.841777,
      "coordSource": "census",
      "portalUrl": "https://maricopacountyaz-energovweb.tylerhost.net/apps/selfservice#/permit/dec05adb-a352-4102-b4c0-23e0e75beccc",
      "notes": ""
    },
    {
      "id": "BLDR2507438",
      "isNew": false,
      "bucket": "ry",
      "address": "35536 W HAMMOND DR TONOPAH AZ 85354",
      "zip": "85354",
      "status": "Expired",
      "statusLabel": "Expired",
      "applied": "2025-09-17",
      "issued": "2025-09-19",
      "expire": "2026-03-18",
      "finaled": null,
      "parcel": "506-41-171X",
      "description": "ROOF MOUNTED APS GRID TIE PHOTOVOLTAIC SYSTEM INSTALL PER MANUFACTURER'S RECOMMENDATION AND 2017 NEC ARTICLES 690 & 705",
      "systemKW": null,
      "battery": false,
      "batteryModel": null,
      "contractor": null,
      "licenseROC": null,
      "contractorPhone": null,
      "contractorEmail": null,
      "valuation": null,
      "owner": "HOOKER PHILLIP M/KATHY",
      "ownerType": "Individual",
      "lastSold": "2005-05-01",
      "parcelType": "Mobile Home",
      "satelliteStatus": "clear",
      "lat": 33.42391,
      "lng": -112.816481,
      "coordSource": "census",
      "portalUrl": "https://maricopacountyaz-energovweb.tylerhost.net/apps/selfservice#/permit/0fbff63a-9aab-415f-a93a-b32b80f7bdca",
      "notes": ""
    },
    {
      "id": "BLDR2506027",
      "isNew": true,
      "bucket": "ry",
      "address": "3320 N 329TH DR TONOPAH AZ 85354",
      "zip": "85354",
      "status": "Expired",
      "statusLabel": "Expired",
      "applied": "2025-07-29",
      "issued": "2025-08-01",
      "expire": null,
      "finaled": null,
      "parcel": "504-09-052",
      "description": "ROOF MOUNTED APS GRID TIE PHOTOVOLTAIC SYSTEM INSTALL PER MANUFACTURER'S RECOMMENDATION AND 2017 NEC ARTICLES 690 & 705",
      "systemKW": null,
      "battery": false,
      "batteryModel": null,
      "contractor": null,
      "licenseROC": null,
      "contractorPhone": null,
      "contractorEmail": null,
      "valuation": null,
      "owner": null,
      "ownerType": null,
      "lastSold": null,
      "parcelType": null,
      "satelliteStatus": "clear",
      "lat": 33.48573,
      "lng": -112.761655,
      "coordSource": "google-geocoded",
      "portalUrl": "https://maricopacountyaz-energovweb.tylerhost.net/apps/selfservice#/permit/BLDR2506027",
      "notes": "EXPIRED. No battery — pitch storage. Owner lookup pending (Rule 4). New permit from Jul 2025 pull."
    },
    {
      "id": "BLDR2504155",
      "isNew": true,
      "bucket": "ry",
      "address": "5703 S 339TH AVE TONOPAH AZ 85354",
      "zip": "85354",
      "status": "Withdrawn",
      "statusLabel": "Withdrawn",
      "applied": "2025-05-21",
      "issued": "2025-05-27",
      "expire": null,
      "finaled": null,
      "parcel": "504-32-188",
      "description": "ROOF MOUNTED APS GRID TIE PHOTOVOLTAIC SYSTEM // TESLA POWERWALL 3 BATTERY // INSTALL PER MANUFACTURER'S RECOMMENDATION AND 2017 NEC ARTICLES 690 & 705",
      "systemKW": null,
      "battery": true,
      "batteryModel": "Tesla Powerwall 3",
      "contractor": null,
      "licenseROC": null,
      "contractorPhone": null,
      "contractorEmail": null,
      "valuation": null,
      "owner": null,
      "ownerType": null,
      "lastSold": null,
      "parcelType": null,
      "satelliteStatus": "clear",
      "lat": 33.394719,
      "lng": -112.781192,
      "coordSource": "census",
      "portalUrl": "https://maricopacountyaz-energovweb.tylerhost.net/apps/selfservice#/permit/BLDR2504155",
      "notes": "WITHDRAWN. Tesla Powerwall 3. Owner lookup pending. New record — not in previous pull."
    },
    {
      "id": "BLDR2600645",
      "isNew": true,
      "bucket": "ry",
      "address": "113 E MARICOPA RD BUCKEYE AZ 85326",
      "zip": "85326",
      "status": "Issued",
      "statusLabel": "Issued — STALLED 73 days",
      "applied": "2026-01-27",
      "issued": "2026-02-09",
      "expire": null,
      "finaled": null,
      "parcel": "504-53-100A",
      "description": "ROOF MOUNTED APS GRID TIE PHOTOVOLTAIC SYSTEM // TESLA POWERWALL 3 BATTERY // INSTALL PER MANUFACTURER'S RECOMMENDATION AND 2017 NEC ARTICLES 690 & 705",
      "systemKW": null,
      "battery": true,
      "batteryModel": "Tesla Powerwall 3",
      "contractor": null,
      "licenseROC": null,
      "contractorPhone": null,
      "contractorEmail": null,
      "valuation": null,
      "owner": null,
      "ownerType": null,
      "lastSold": null,
      "parcelType": null,
      "satelliteStatus": "clear",
      "lat": 33.384709,
      "lng": -112.584018,
      "coordSource": "census",
      "portalUrl": "https://maricopacountyaz-energovweb.tylerhost.net/apps/selfservice#/permit/BLDR2600645",
      "notes": "STALLED 73 days. Same address as BLDR2509950 (Tarpley). NEW record — not in prior pull. Tesla Powerwall 3."
    },
    {
      "id": "BLDR2600600",
      "isNew": false,
      "bucket": "ry",
      "address": "12319 S 204TH LN BUCKEYE AZ 85326",
      "zip": "85326",
      "status": "Issued",
      "statusLabel": "Issued — STALLED 83 days",
      "applied": "2026-01-27",
      "issued": "2026-01-30",
      "expire": "2026-08-31",
      "finaled": null,
      "parcel": "400-53-269",
      "description": "ROOF MOUNTED APS GRID TIE PHOTOVOLTAIC SYSTEM // TESLA POWERWALL 3 BATTERY // INSTALL PER MANUFACTURER'S RECOMMENDATION AND 2017 NEC ARTICLES 690 & 705",
      "systemKW": null,
      "battery": true,
      "batteryModel": "Tesla Powerwall 3",
      "contractor": "Our World Energy",
      "licenseROC": "",
      "contractorPhone": "623-850-5700",
      "contractorEmail": "permits@ourworldenergy.com",
      "valuation": 21450,
      "owner": "Luis Arreola Cervantes & Ivette Stephanie Martinez",
      "ownerType": "Individual",
      "lastSold": "2025-02-01",
      "parcelType": "Land",
      "satelliteStatus": "clear",
      "lat": 33.318988,
      "lng": -112.490814,
      "coordSource": "google-geocoded",
      "portalUrl": "https://maricopacountyaz-energovweb.tylerhost.net/apps/selfservice#/permit/d027674f-b71f-4353-be8d-efe1bf3966e5",
      "notes": "STALLED 83 days. Our World Energy. Est kW: ≈5.7 kW (est from $21,450 - $10,000 / $2,000). Recent buyer (Feb 2025). Parcel still listed as Land — house may be new construction."
    },
    {
      "id": "BLDR2600453",
      "isNew": false,
      "bucket": "ry",
      "address": "20369 W CARVER RD BUCKEYE AZ 85326",
      "zip": "85326",
      "status": "Issued",
      "statusLabel": "Issued — STALLED 87 days",
      "applied": "2026-01-21",
      "issued": "2026-01-26",
      "expire": "2026-07-25",
      "finaled": null,
      "parcel": "400-53-275",
      "description": "ROOF MOUNTED APS GRID TIE PHOTOVOLTAIC SYSTEM // SOLAREDHE HOME BATTERY // INSTALL PER MANUFACTURER'S RECOMMENDATION AND 2017 NEC ARTICLES 690 & 705",
      "systemKW": null,
      "battery": true,
      "batteryModel": "SolarEdge Home Battery",
      "contractor": "Our World Energy",
      "licenseROC": "",
      "contractorPhone": "623-850-5700",
      "contractorEmail": "permits@ourworldenergy.com",
      "valuation": 27800,
      "owner": "Fabian Rojo Rodriguez & Lidia E Arrayales Arreola",
      "ownerType": "Individual",
      "lastSold": "2025-06-01",
      "parcelType": "Land",
      "satelliteStatus": "clear",
      "lat": 33.340796,
      "lng": -112.488346,
      "coordSource": "nominatim",
      "portalUrl": "https://maricopacountyaz-energovweb.tylerhost.net/apps/selfservice#/permit/afa29aad-f8ff-4b87-a717-732de8206e2e",
      "notes": "STALLED 87 days. Our World Energy, SolarEdge battery. Est kW: ≈8.9 kW (est from $27,800 - $10,000 / $2,000). Recent buyer (Jun 2025). Note description has typo 'SOLAREDHE' — likely SolarEdge."
    },
    {
      "id": "BLDR2602684",
      "isNew": true,
      "bucket": "ry",
      "address": "11305 S 195TH DR BUCKEYE AZ 85326",
      "zip": "85326",
      "status": "Denied",
      "statusLabel": "Denied",
      "applied": "2026-04-06",
      "issued": null,
      "expire": null,
      "finaled": null,
      "parcel": "400-83-019",
      "description": "NEW PHOTOVOLTAIC FLAT ROOF MOUNTED SYSTEM - 11.440 KW DC/11.440 KW AC WITH BATTERY STORAGE SYSTEM // INSTALL PER MANUFACTURER'S RECOMMENDATION AND 2017 NEC ARTICLES 690 & 705",
      "systemKW": 11.44,
      "battery": true,
      "batteryModel": null,
      "contractor": null,
      "licenseROC": null,
      "contractorPhone": null,
      "contractorEmail": null,
      "valuation": null,
      "owner": null,
      "ownerType": null,
      "lastSold": null,
      "parcelType": null,
      "satelliteStatus": "solar-detected",
      "lat": 33.343979,
      "lng": -112.470666,
      "coordSource": "census",
      "portalUrl": "https://maricopacountyaz-energovweb.tylerhost.net/apps/selfservice#/permit/BLDR2602684",
      "notes": "DENIED 17 days ago. Same address as BLDR2509075 (YANNONE). 11.44 kW flat roof — flat roof may be denial reason. Large system with battery. Same parcel denied twice — worth a door knock."
    },
    {
      "id": "BLDR2601382",
      "isNew": false,
      "bucket": "ry",
      "address": "20334 W RAINBOW BLVD BUCKEYE AZ 85326",
      "zip": "85326",
      "status": "Withdrawn",
      "statusLabel": "Withdrawn",
      "applied": "2026-02-20",
      "issued": null,
      "expire": null,
      "finaled": null,
      "parcel": "400-62-301",
      "description": "installing a ground mount solar system with one battery",
      "systemKW": null,
      "battery": true,
      "batteryModel": null,
      "contractor": null,
      "licenseROC": null,
      "contractorPhone": null,
      "contractorEmail": null,
      "valuation": null,
      "owner": "ABERNATHY-CASTLE LIVING TRUST",
      "ownerType": "Entity",
      "lastSold": null,
      "parcelType": "Mobile Home",
      "satelliteStatus": "verify",
      "lat": 33.254278,
      "lng": -112.5029,
      "coordSource": "census",
      "portalUrl": "https://maricopacountyaz-energovweb.tylerhost.net/apps/selfservice#/permit/832a3d72-f9a1-4c34-b6bb-713b7d1baf81",
      "notes": "WITHDRAWN. Ground mount solar — different install than rooftop. Trust ownership. Battery included."
    },
    {
      "id": "BLDR2509950",
      "isNew": false,
      "bucket": "ry",
      "address": "113 E MARICOPA RD BUCKEYE AZ 85326",
      "zip": "85326",
      "status": "Withdrawn",
      "statusLabel": "Withdrawn",
      "applied": "2025-12-16",
      "issued": "2025-12-19",
      "expire": "2026-06-17",
      "finaled": null,
      "parcel": "504-53-100A",
      "description": "ROOF MOUNTED APS GRID TIE PHOTOVOLTAIC SYSTEM POWERWALL 3 BATTERY WITH MAIN SERVICE PANEL UPGRADE TO 225A SOLAR READY // INSTALL PER MANUFACTURER'S RECOMMENDATION AND 2017 NEC ARTICLES 690 & 705",
      "systemKW": null,
      "battery": true,
      "batteryModel": "Tesla Powerwall 3",
      "contractor": null,
      "licenseROC": null,
      "contractorPhone": null,
      "contractorEmail": null,
      "valuation": null,
      "owner": "TARPLEY LARRY P/BERTHA M",
      "ownerType": "Individual",
      "lastSold": null,
      "parcelType": "Residential",
      "satelliteStatus": "clear",
      "lat": 33.384709,
      "lng": -112.584018,
      "coordSource": "census",
      "portalUrl": "https://maricopacountyaz-energovweb.tylerhost.net/apps/selfservice#/permit/9d0ee3d4-c716-409f-9843-a87bea607145",
      "notes": "WITHDRAWN. Powerwall 3 + MPU 225A Solar Ready. Same address now has new stalled permit BLDR2600645 — may have refiled."
    },
    {
      "id": "BLDR2510070",
      "isNew": true,
      "bucket": "ry",
      "address": "8612 S 204TH DR BUCKEYE AZ 85326",
      "zip": "85326",
      "status": "Denied",
      "statusLabel": "Denied",
      "applied": "2025-12-18",
      "issued": null,
      "expire": null,
      "finaled": null,
      "parcel": "400-09-004B",
      "description": "ROOF MOUNTED APS GRID TIE PHOTOVOLTAIC SYSTEM // INTEGRATED TESLA BATTERY // INSTALL PER MANUFACTURER'S RECOMMENDATION AND 2017 NEC ARTICLES 690 & 705",
      "systemKW": null,
      "battery": true,
      "batteryModel": "Tesla Integrated (Powerwall 3)",
      "contractor": null,
      "licenseROC": null,
      "contractorPhone": null,
      "contractorEmail": null,
      "valuation": null,
      "owner": null,
      "ownerType": null,
      "lastSold": null,
      "parcelType": null,
      "satelliteStatus": "clear",
      "lat": 33.368446,
      "lng": -112.489057,
      "coordSource": "census",
      "portalUrl": "https://maricopacountyaz-energovweb.tylerhost.net/apps/selfservice#/permit/BLDR2510070",
      "notes": "DENIED Dec 2025. Tesla Integrated battery. Owner lookup pending. Denial reason unknown — prime pitch: 'the other guys' permit got denied, we can help.'"
    },
    {
      "id": "BLDR2509075",
      "isNew": false,
      "bucket": "ry",
      "address": "11305 S 195TH DR BUCKEYE AZ 85326",
      "zip": "85326",
      "status": "Withdrawn",
      "statusLabel": "Withdrawn",
      "applied": "2025-11-13",
      "issued": "2025-11-24",
      "expire": "2026-05-23",
      "finaled": null,
      "parcel": "400-83-019",
      "description": "ROOF MOUNTED APS GRID TIE PHOTOVOLTAIC SYSTEM // INTEGRATED TESLA BATTERY // INSTALL PER MANUFACTURER'S RECOMMENDATION AND 2017 NEC ARTICLES 690 & 705",
      "systemKW": null,
      "battery": true,
      "batteryModel": "Tesla Integrated (Powerwall 3)",
      "contractor": null,
      "licenseROC": null,
      "contractorPhone": null,
      "contractorEmail": null,
      "valuation": null,
      "owner": "YANNONE ANTHONY W",
      "ownerType": "Individual",
      "lastSold": null,
      "parcelType": "Residential",
      "satelliteStatus": "solar-detected",
      "lat": 33.343979,
      "lng": -112.470666,
      "coordSource": "census",
      "portalUrl": "https://maricopacountyaz-energovweb.tylerhost.net/apps/selfservice#/permit/ad54a796-bc79-4edb-91b5-ef07fc68eeb3",
      "notes": "WITHDRAWN. YANNONE ANTHONY W. Same address now has Denied permit BLDR2602684 — two failed attempts. Very motivated homeowner."
    },
    {
      "id": "BLDR2508599",
      "isNew": false,
      "bucket": "ry",
      "address": "12856 S ZUNI RD BUCKEYE AZ 85326",
      "zip": "85326",
      "status": "Withdrawn",
      "statusLabel": "Withdrawn",
      "applied": "2025-10-29",
      "issued": "2025-10-31",
      "expire": "2026-04-29",
      "finaled": null,
      "parcel": "400-76-043",
      "description": "ROOF MOUNTED APS GRID TIE PHOTOVOLTAIC SYSTEM // INTEGRATED TESLA BATTERY // INSTALL PER MANUFACTURER'S RECOMMENDATION AND 2017 NEC ARTICLES 690 & 705",
      "systemKW": null,
      "battery": true,
      "batteryModel": "Tesla Integrated (Powerwall 3)",
      "contractor": null,
      "licenseROC": null,
      "contractorPhone": null,
      "contractorEmail": null,
      "valuation": null,
      "owner": "REICHENBERGER ROBERT M JR/SANDRA D",
      "ownerType": "Individual",
      "lastSold": null,
      "parcelType": "Residential",
      "satelliteStatus": "solar-detected",
      "lat": 33.329575,
      "lng": -112.486243,
      "coordSource": "census",
      "portalUrl": "https://maricopacountyaz-energovweb.tylerhost.net/apps/selfservice#/permit/0fcbd612-c121-42fe-941d-5fcdc54175ae",
      "notes": "WITHDRAWN. Tesla Integrated. Same address as BLDR2602943 (new permit just applied Apr 15 2026 — refiled!). Hot lead — they're trying again."
    },
    {
      "id": "BLDR2506917",
      "isNew": false,
      "bucket": "ry",
      "address": "1024 N 193RD AVE BUCKEYE AZ 85326",
      "zip": "85326",
      "status": "Withdrawn",
      "statusLabel": "Withdrawn",
      "applied": "2025-08-28",
      "issued": "2025-09-03",
      "expire": "2026-03-02",
      "finaled": null,
      "parcel": "502-36-011C",
      "description": "ROOF MOUNTED APS GRID TIE PHOTOVOLTAIC SYSTEM WHICH INCLUDES REDUCTION OF MAIN CIRCUIT BREAKER TO 175 AMPS // INSTALL PER MANUFACTURER'S RECOMMENDATION AND 2017 NEC ARTICLES 690 & 705",
      "systemKW": null,
      "battery": false,
      "batteryModel": null,
      "contractor": null,
      "licenseROC": null,
      "contractorPhone": null,
      "contractorEmail": null,
      "valuation": null,
      "owner": "LOPEZ FAMILY LIVING TRUST",
      "ownerType": "Entity",
      "lastSold": null,
      "parcelType": "Residential",
      "satelliteStatus": "clear",
      "lat": 33.457818,
      "lng": -112.474533,
      "coordSource": "census",
      "portalUrl": "https://maricopacountyaz-energovweb.tylerhost.net/apps/selfservice#/permit/739a7c08-6fca-4496-9b43-18b14c3dd7be",
      "notes": "WITHDRAWN. Trust ownership. No battery — pitch storage. Main breaker reduction to 175A included."
    },
    {
      "id": "BLDR2505156",
      "isNew": true,
      "bucket": "ry",
      "address": "2030 S TUTHILL RD BUCKEYE AZ 85326",
      "zip": "85326",
      "status": "Expired",
      "statusLabel": "Expired",
      "applied": "2025-06-27",
      "issued": "2025-07-01",
      "expire": null,
      "finaled": null,
      "parcel": "502-47-945L",
      "description": "ROOF MOUNTED APS GRID TIE PHOTOVOLTAIC SYSTEM INSTALL PER MANUFACTURER'S RECOMMENDATION AND 2017 NEC ARTICLES 690 & 705",
      "systemKW": null,
      "battery": false,
      "batteryModel": null,
      "contractor": null,
      "licenseROC": null,
      "contractorPhone": null,
      "contractorEmail": null,
      "valuation": null,
      "owner": null,
      "ownerType": null,
      "lastSold": null,
      "parcelType": null,
      "satelliteStatus": "clear",
      "lat": 33.428196,
      "lng": -112.496157,
      "coordSource": "census",
      "portalUrl": "https://maricopacountyaz-energovweb.tylerhost.net/apps/selfservice#/permit/BLDR2505156",
      "notes": "EXPIRED. No battery. Owner lookup pending."
    },
    {
      "id": "BLDR2503908",
      "isNew": true,
      "bucket": "ry",
      "address": "23045 W HOPI ST BUCKEYE AZ 85326",
      "zip": "85326",
      "status": "Denied",
      "statusLabel": "Denied",
      "applied": "2025-05-12",
      "issued": null,
      "expire": null,
      "finaled": null,
      "parcel": "504-63-526",
      "description": "ROOFTOP SOLAR PANEL INSTALLATION",
      "systemKW": null,
      "battery": false,
      "batteryModel": null,
      "contractor": null,
      "licenseROC": null,
      "contractorPhone": null,
      "contractorEmail": null,
      "valuation": null,
      "owner": null,
      "ownerType": null,
      "lastSold": null,
      "parcelType": null,
      "satelliteStatus": "clear",
      "lat": 33.429534,
      "lng": -112.546438,
      "coordSource": "census",
      "portalUrl": "https://maricopacountyaz-energovweb.tylerhost.net/apps/selfservice#/permit/BLDR2503908",
      "notes": "DENIED May 2025. Vague description — no system size visible. Owner lookup pending."
    },
    {
      "id": "BLDR2503626",
      "isNew": true,
      "bucket": "ry",
      "address": "308 3RD AVE E BUCKEYE AZ 85326",
      "zip": "85326",
      "status": "Expired",
      "statusLabel": "Expired",
      "applied": "2025-05-01",
      "issued": "2025-05-09",
      "expire": null,
      "finaled": null,
      "parcel": "504-51-068",
      "description": "ROOF MOUNTED APS GRID TIE PHOTOVOLTAIC SYSTEM //INTEGRATED SOLAREDGE BATTERY// INSTALL PER MANUFACTURER'S RECOMMENDATION AND 2017 NEC ARTICLES 690 & 705",
      "systemKW": null,
      "battery": true,
      "batteryModel": "SolarEdge Home Battery",
      "contractor": null,
      "licenseROC": null,
      "contractorPhone": null,
      "contractorEmail": null,
      "valuation": null,
      "owner": null,
      "ownerType": null,
      "lastSold": null,
      "parcelType": null,
      "satelliteStatus": "clear",
      "lat": 33.380382,
      "lng": -112.580938,
      "coordSource": "census",
      "portalUrl": "https://maricopacountyaz-energovweb.tylerhost.net/apps/selfservice#/permit/BLDR2503626",
      "notes": "EXPIRED. Integrated SolarEdge battery. Owner lookup pending."
    },
    {
      "id": "BLDR2600631",
      "isNew": false,
      "bucket": "ry",
      "address": "22341 W DOVE VALLEY RD WITTMANN AZ 85361",
      "zip": "85361",
      "status": "Issued",
      "statusLabel": "Issued — STALLED 70 days",
      "applied": "2026-01-27",
      "issued": "2026-02-12",
      "expire": "2026-08-11",
      "finaled": null,
      "parcel": "503-39-004N",
      "description": "ROOF MOUNTED APS GRID TIE PHOTOVOLTAIC SYSTEM // INTEGRATED TESLA BATTERY // INSTALL PER MANUFACTURER'S RECOMMENDATION AND 2017 NEC ARTICLES 690 & 705",
      "systemKW": null,
      "battery": true,
      "batteryModel": "Tesla Integrated (Powerwall 3)",
      "contractor": "Green Muscle Solar",
      "licenseROC": "328742",
      "contractorPhone": "480-442-2240",
      "contractorEmail": "permits@greenmusclesolar.com",
      "valuation": 64482,
      "owner": "Yvette & Donald Haughton",
      "ownerType": "Individual",
      "lastSold": "2025-07-01",
      "parcelType": "Residential",
      "satelliteStatus": "clear",
      "lat": 33.782113,
      "lng": -112.543851,
      "coordSource": "census",
      "portalUrl": "https://maricopacountyaz-energovweb.tylerhost.net/apps/selfservice#/permit/aa5b34ab-8234-4998-887e-1a7e45298ea2",
      "notes": "STALLED 70 days. Green Muscle Solar, ROC 328742. Est kW: ≈27.2 kW (est from $64,482 - $10,000 / $2,000) — very large system. Recent buyer (Jul 2025). Same address as withdrawn BLDR2509106."
    },
    {
      "id": "BLDR2600061",
      "isNew": false,
      "bucket": "ry",
      "address": "25505 W BROOKHART WAY WITTMANN AZ 85361",
      "zip": "85361",
      "status": "Issued",
      "statusLabel": "Issued — STALLED 92 days",
      "applied": "2026-01-06",
      "issued": "2026-01-21",
      "expire": "2026-07-20",
      "finaled": null,
      "parcel": "503-32-496A",
      "description": "ROOF MOUNTED APS GRID TIE PHOTOVOLTAIC SYSTEM INSTALL PER MANUFACTURER'S RECOMMENDATION AND 2017 NEC ARTICLES 690 & 705",
      "systemKW": null,
      "battery": false,
      "batteryModel": null,
      "contractor": "Freedom Forever Arizona",
      "licenseROC": "",
      "contractorPhone": "602-888-7196",
      "contractorEmail": "permitsarizona@freedomforever.com",
      "valuation": 12858,
      "owner": "Jordan A & Amber Schauer",
      "ownerType": "Individual",
      "lastSold": "2025-11-01",
      "parcelType": "Land",
      "satelliteStatus": "clear",
      "lat": 33.741413,
      "lng": -112.612173,
      "coordSource": "nominatim",
      "portalUrl": "https://maricopacountyaz-energovweb.tylerhost.net/apps/selfservice#/permit/d5e059a5-04c9-448f-abe3-e97bf78cb7ed",
      "notes": "STALLED 92 days. Freedom Forever AZ. Est kW: ≈6.4 kW (est from $12,858 / $2,000). No battery — retrofit opportunity. Recent buyer (Nov 2025). Parcel listed as Land — new build?"
    },
    {
      "id": "BLDR2509106",
      "isNew": false,
      "bucket": "ry",
      "address": "22341 W DOVE VALLEY RD WITTMANN AZ 85361",
      "zip": "85361",
      "status": "Withdrawn",
      "statusLabel": "Withdrawn",
      "applied": "2025-11-13",
      "issued": "2025-11-24",
      "expire": "2026-05-23",
      "finaled": null,
      "parcel": "503-39-004N",
      "description": "ROOF MOUNTED APS GRID TIE PHOTOVOLTAIC SYSTEM // INTEGRATED TESLA BATTERY // INSTALL PER MANUFACTURER'S RECOMMENDATION AND 2017 NEC ARTICLES 690 & 705",
      "systemKW": null,
      "battery": true,
      "batteryModel": "Tesla Integrated (Powerwall 3)",
      "contractor": null,
      "licenseROC": null,
      "contractorPhone": null,
      "contractorEmail": null,
      "valuation": null,
      "owner": "HAUGHTON YVETTE/DONALD",
      "ownerType": "Individual",
      "lastSold": "2025-07-01",
      "parcelType": "Residential",
      "satelliteStatus": "clear",
      "lat": 33.782113,
      "lng": -112.543851,
      "coordSource": "census",
      "portalUrl": "https://maricopacountyaz-energovweb.tylerhost.net/apps/selfservice#/permit/eb1d97de-a429-4a51-baee-00273e5de52c",
      "notes": "WITHDRAWN. Same address now has stalled BLDR2600631 (refiled). Haughton family."
    },
    {
      "id": "BLDR2504762",
      "isNew": true,
      "bucket": "ry",
      "address": "30116 N 206TH AVE WITTMANN AZ 85361",
      "zip": "85361",
      "status": "Expired",
      "statusLabel": "Expired",
      "applied": "2025-06-12",
      "issued": "2025-07-01",
      "expire": null,
      "finaled": null,
      "parcel": "503-48-525",
      "description": "ROOF MOUNTED APS GRID TIE PHOTOVOLTAIC SYSTEM // INTEGRATED TESLA BATTERY // INSTALL PER MANUFACTURER'S RECOMMENDATION AND 2017 NEC ARTICLES 690 & 705",
      "systemKW": null,
      "battery": true,
      "batteryModel": "Tesla Integrated (Powerwall 3)",
      "contractor": null,
      "licenseROC": null,
      "contractorPhone": null,
      "contractorEmail": null,
      "valuation": null,
      "owner": null,
      "ownerType": null,
      "lastSold": null,
      "parcelType": null,
      "satelliteStatus": "clear",
      "lat": 33.756401,
      "lng": -112.505713,
      "coordSource": "census",
      "portalUrl": "https://maricopacountyaz-energovweb.tylerhost.net/apps/selfservice#/permit/BLDR2504762",
      "notes": "EXPIRED. Tesla Integrated battery. Owner lookup pending."
    },
    {
      "id": "BLDR2506138",
      "isNew": true,
      "bucket": "ry",
      "address": "469 LIESEN DR MORRISTOWN AZ 85342",
      "zip": "85342",
      "status": "Expired",
      "statusLabel": "Expired",
      "applied": "2025-08-01",
      "issued": "2025-08-05",
      "expire": null,
      "finaled": null,
      "parcel": "503-86-215A",
      "description": "ROOF MOUNTED APS GRID TIE PHOTOVOLTAIC SYSTEM INSTALL PER MANUFACTURER'S RECOMMENDATION AND 2017 NEC ARTICLES 690 & 705",
      "systemKW": null,
      "battery": false,
      "batteryModel": null,
      "contractor": null,
      "licenseROC": null,
      "contractorPhone": null,
      "contractorEmail": null,
      "valuation": null,
      "owner": null,
      "ownerType": null,
      "lastSold": null,
      "parcelType": null,
      "satelliteStatus": "clear",
      "lat": 33.814081,
      "lng": -112.585403,
      "coordSource": "census",
      "portalUrl": "https://maricopacountyaz-energovweb.tylerhost.net/apps/selfservice#/permit/BLDR2506138",
      "notes": "EXPIRED. Morristown — northernmost zip. No battery — retrofit pitch. Owner lookup pending.",
      "outcome": "hassolar",
      "outcomeDate": "2026-04-24T20:28:39.808Z"
    },
    {
      "id": "BLDR2508280",
      "isNew": true,
      "bucket": "ry",
      "address": "8606 W KINGMAN ST TOLLESON AZ 85353",
      "zip": "85353",
      "status": "Denied",
      "statusLabel": "Denied",
      "applied": "2025-10-17",
      "issued": null,
      "expire": null,
      "finaled": null,
      "parcel": "101-30-095",
      "description": "ROOF MOUNTED APS GRID TIE PHOTOVOLTAIC SYSTEM INSTALL PER MANUFACTURER'S RECOMMENDATION AND 2017 NEC ARTICLES 690 & 705",
      "systemKW": null,
      "battery": false,
      "batteryModel": null,
      "contractor": null,
      "licenseROC": null,
      "contractorPhone": null,
      "contractorEmail": null,
      "valuation": null,
      "owner": null,
      "ownerType": null,
      "lastSold": null,
      "parcelType": null,
      "satelliteStatus": "clear",
      "lat": 33.420225,
      "lng": -112.245084,
      "coordSource": "census",
      "portalUrl": "https://maricopacountyaz-energovweb.tylerhost.net/apps/selfservice#/permit/BLDR2508280",
      "notes": "DENIED. Tolleson edge of territory. No battery. Owner lookup pending. Denial reason unknown."
    },
    {
      "id": "BLDR2602924",
      "isNew": true,
      "bucket": "fi",
      "address": "817 N 375TH AVE TONOPAH AZ 85354",
      "zip": "85354",
      "status": "Issued",
      "statusLabel": "Issued — 3 days ago 🔥",
      "applied": "2026-04-14",
      "issued": "2026-04-20",
      "expire": null,
      "finaled": null,
      "parcel": "—",
      "description": "ROOF MOUNTED APS GRID TIE PHOTOVOLTAIC SYSTEM // INTEGRATED TESLA BATTERY // INSTALL PER MANUFACTURER'S RECOMMENDATION AND 2017 NEC ARTICLES 690 & 705",
      "systemKW": null,
      "battery": true,
      "batteryModel": "Tesla Integrated (Powerwall 3)",
      "contractor": null,
      "licenseROC": null,
      "contractorPhone": null,
      "contractorEmail": null,
      "valuation": null,
      "owner": null,
      "ownerType": null,
      "lastSold": null,
      "parcelType": null,
      "satelliteStatus": "clear",
      "lat": 33.454016,
      "lng": -112.858965,
      "coordSource": "census",
      "portalUrl": "https://maricopacountyaz-energovweb.tylerhost.net/apps/selfservice#/permit/BLDR2602924",
      "notes": "ISSUED 3 DAYS AGO — top priority. Tesla Integrated battery. Owner/contractor lookup pending (Rule 4/5). NEW — not in prior pull."
    },
    {
      "id": "BLDR2602821",
      "isNew": false,
      "bucket": "fi",
      "address": "9413 S 543RD AVE TONOPAH AZ 85354",
      "zip": "85354",
      "status": "Issued",
      "statusLabel": "Issued — 8 days ago",
      "applied": "2026-04-10",
      "issued": "2026-04-15",
      "expire": "2026-10-12",
      "finaled": null,
      "parcel": "401-57-402A",
      "description": "ROOF MOUNTED APS GRID TIE PHOTOVOLTAIC SYSTEM // INTEGRATED TESLA BATTERY // INSTALL PER MANUFACTURER'S RECOMMENDATION AND 2017 NEC ARTICLES 690 & 705",
      "systemKW": null,
      "battery": true,
      "batteryModel": "Tesla Integrated (Powerwall 3)",
      "contractor": "United Energy Partners",
      "licenseROC": "344599",
      "contractorPhone": "480-226-1383",
      "contractorEmail": "scott.wahlstrom@uepsolar.com",
      "valuation": 29450,
      "owner": "Eddie Duane Combs & Susan Corbin",
      "ownerType": "Individual",
      "lastSold": null,
      "parcelType": "Residential",
      "satelliteStatus": "clear",
      "lat": 33.360667,
      "lng": -113.220767,
      "coordSource": "census",
      "portalUrl": "https://maricopacountyaz-energovweb.tylerhost.net/apps/selfservice#/permit/e19ff565-9366-4477-aa9b-66c7e80c4b60",
      "notes": "ISSUED 8 DAYS AGO. United Energy Partners, ROC 344599. Est kW: ≈9.7 kW (est from $29,450 - $10,000 / $2,000). Rural dwelling. Satellite showed no panels."
    },
    {
      "id": "BLDR2602370",
      "isNew": false,
      "bucket": "fi",
      "address": "37217 W POLK ST TONOPAH AZ 85354",
      "zip": "85354",
      "status": "Issued",
      "statusLabel": "Issued — 17 days ago",
      "applied": "2026-03-25",
      "issued": "2026-04-06",
      "expire": "2026-10-03",
      "finaled": null,
      "parcel": "506-40-004G",
      "description": "INSTALLATION OF PV BATTERY STORAGE TESLA POWERWALL 3 WITH 11.5 kWh PV STORAGE CAPACITY // INSTALL PER MANUFACTURER'S RECOMMENDATION AND 2017 NEC ARTICLES 690 & 705",
      "systemKW": null,
      "battery": true,
      "batteryModel": "Tesla Powerwall 3",
      "contractor": "SunX Solutions LLC",
      "licenseROC": "",
      "contractorPhone": "623-640-3032",
      "contractorEmail": "Rlopez@sunxsolutions.com",
      "valuation": 14000,
      "owner": "Familia Martinez Revocable Living Trust",
      "ownerType": "Entity",
      "lastSold": null,
      "parcelType": "Mobile Home",
      "satelliteStatus": "clear",
      "lat": 33.451201,
      "lng": -112.853416,
      "coordSource": "census",
      "portalUrl": "https://maricopacountyaz-energovweb.tylerhost.net/apps/selfservice#/permit/1f570d38-21fc-4879-b524-5edeadc58156",
      "notes": "",
      "outcome": "hassolar",
      "outcomeDate": "2026-04-24T01:26:22.588Z"
    },
    {
      "id": "BLDR2602524",
      "isNew": false,
      "bucket": "fi",
      "address": "33125 W EUCLID AVE TONOPAH AZ 85354",
      "zip": "85354",
      "status": "Issued",
      "statusLabel": "Issued — 14 days ago",
      "applied": "2026-03-31",
      "issued": "2026-04-09",
      "expire": "2026-10-06",
      "finaled": null,
      "parcel": "401-42-537",
      "description": "ROOF MOUNTED APS GRID TIE PHOTOVOLTAIC SYSTEM INSTALL PER MANUFACTURER'S RECOMMENDATION AND 2017 NEC ARTICLES 690 & 705",
      "systemKW": null,
      "battery": false,
      "batteryModel": null,
      "contractor": "Bright Home Energy",
      "licenseROC": "",
      "contractorPhone": "480-656-9538",
      "contractorEmail": "permits@brighthomeenergy.com",
      "valuation": 12012,
      "owner": "Lisa Kaye Rose Casavant, Anthony Wayne & Nickolas Dahl",
      "ownerType": "Individual",
      "lastSold": "2026-02-01",
      "parcelType": "Mobile Home",
      "satelliteStatus": "clear",
      "lat": 33.366214,
      "lng": -112.767023,
      "coordSource": "census",
      "portalUrl": "https://maricopacountyaz-energovweb.tylerhost.net/apps/selfservice#/permit/d68d0d72-1cd3-4468-b374-098980008309",
      "notes": "",
      "outcome": "hassolar",
      "outcomeDate": "2026-04-24T01:28:17.594Z"
    },
    {
      "id": "BLDR2602291",
      "isNew": false,
      "bucket": "fi",
      "address": "2907 N 391ST AVE TONOPAH AZ 85354",
      "zip": "85354",
      "status": "Issued",
      "statusLabel": "Issued — 14 days ago",
      "applied": "2026-03-23",
      "issued": "2026-04-09",
      "expire": "2026-10-10",
      "finaled": null,
      "parcel": "506-45-150A",
      "description": "ROOF MOUNTED APS GRID TIE PHOTOVOLTAIC SYSTEM INSTALL PER MANUFACTURER'S RECOMMENDATION AND 2017 NEC ARTICLES 690 & 705",
      "systemKW": null,
      "battery": false,
      "batteryModel": null,
      "contractor": "Independent Solar LLC",
      "licenseROC": "",
      "contractorPhone": "480-408-4986",
      "contractorEmail": "permitting@independentsolar.com",
      "valuation": 24265,
      "owner": "Estellar V Nelson & Bishop V Ybarra",
      "ownerType": "Individual",
      "lastSold": "2026-03-01",
      "parcelType": "Mobile Home",
      "satelliteStatus": "verify",
      "lat": 33.479505,
      "lng": -112.894502,
      "coordSource": "census",
      "portalUrl": "https://maricopacountyaz-energovweb.tylerhost.net/apps/selfservice#/permit/c93c5d8e-753f-4ef1-a3aa-5ca285b87e76",
      "notes": "",
      "outcome": "hassolar",
      "outcomeDate": "2026-04-24T01:22:59.207Z"
    }
  ],
  "lastUpdated": "2026-04-24T20:28:39.809Z"
}